{
  "generatedAt": "2026-02-02T08:00:55Z",
  "categories": [
    {
      "category": "uncategorized",
      "count": 2,
      "plugins": [
        {
          "name": "marketplace-manager",
          "version": "1.1.0",
          "description": "Manage the fakoli-plugins marketplace: add/remove plugins, validate manifests, and regenerate registry indices",
          "path": "plugins/marketplace-manager"
        },
        {
          "name": "nano-banana-pro",
          "version": "1.2.0",
          "description": "Generate, edit, remix, and optimize images using Google's Gemini 3 Pro Image Preview model",
          "path": "plugins/nano-banana-pro"
        }
      ]
    }
  ]
}
